nightcrawler/__init__.py
nightcrawler/addon.py
nightcrawler/config.py
nightcrawler/crawler.py
nightcrawler/passive_scanner.py
nightcrawler/runner.py
nightcrawler/sqli_scanner.py
nightcrawler/utils.py
nightcrawler/websocket_handler.py
nightcrawler/xss_scanner.py
nightcrawler/active_scans/__init__.py
nightcrawler/active_scans/discovery.py
nightcrawler/active_scans/traversal.py
nightcrawler/passive_scans/__init__.py
nightcrawler/passive_scans/content.py
nightcrawler/passive_scans/cookies.py
nightcrawler/passive_scans/headers.py
nightcrawler/passive_scans/javascript.py
nightcrawler/passive_scans/jwt.py
nightcrawler/passive_scans/websockets.py
nightcrawler_mitm-0.10.0.dist-info/licenses/LICENSE
nightcrawler_mitm-0.10.0.dist-info/METADATA
nightcrawler_mitm-0.10.0.dist-info/WHEEL
nightcrawler_mitm-0.10.0.dist-info/entry_points.txt
nightcrawler_mitm-0.10.0.dist-info/top_level.txt
nightcrawler_mitm-0.10.0.dist-info/RECORD
