Metadata-Version: 2.4
Name: nightcrawler-mitm
Version: 0.10.0
Summary: A mitmproxy addon for background passive analysis, crawling, and basic active scanning, designed as a security researcher's sidekick.
Author-email: thesp0nge <your.email@example.com>
License: MIT License
Project-URL: Homepage, https://github.com/thesp0nge/nightcrawler-mitm
Project-URL: Repository, https://github.com/thesp0nge/nightcrawler-mitm
Project-URL: Bug Tracker, https://github.com/thesp0nge/nightcrawler-mitm/issues
Keywords: mitmproxy,security,scanner,proxy,pentest,xss,sqli,crawler,addon
Classifier: Development Status :: 4 - Beta
Classifier: Environment :: Console
Classifier: Intended Audience :: Developers
Classifier: Intended Audience :: Information Technology
Classifier: License :: OSI Approved :: MIT License
Classifier: Operating System :: OS Independent
Classifier: Programming Language :: Python :: 3.11
Classifier: Programming Language :: Python :: 3.12
Classifier: Topic :: Internet :: Proxy Servers
Classifier: Topic :: Security
Requires-Python: >=3.9
License-File: LICENSE
Requires-Dist: mitmproxy>=10.0.0
Requires-Dist: httpx>=0.25.0
Requires-Dist: beautifulsoup4>=4.10.0
Requires-Dist: PyYAML>=6.0
Dynamic: license-file
